.bzrignore
CHANGES.txt
README.txt
bootstrap.py
buildout.cfg
setup.py
src/publickeymanager/__init__.py
src/publickeymanager/key.cfg
src/publickeymanager/publickeymanager.py
src/publickeymanager/tests.py
src/publickeymanager.egg-info/PKG-INFO
src/publickeymanager.egg-info/SOURCES.txt
src/publickeymanager.egg-info/dependency_links.txt
src/publickeymanager.egg-info/entry_points.txt
src/publickeymanager.egg-info/requires.txt
src/publickeymanager.egg-info/top_level.txt