Metadata-Version: 1.0
Name: publickeymanager
Version: 0.2.3
Summary: Public Key Manager is designed to generate authorized_keys file and to distribute those to specified servers.
Home-page: http://launchpad.net/public-key-manager
Author: Roland van Laar
Author-email: roland@micite.net
License: BSD
Platform: UNKNOWN
Classifier: Intended Audience :: System Administrators
Classifier: License :: OSI Approved :: BSD License
Classifier: Operating System :: POSIX
Classifier: Programming Language :: Python
Classifier: Topic :: System :: Systems Administration
